bolt_api_sdk/__init__.py
bolt_api_sdk/_hooks/__init__.py
bolt_api_sdk/_hooks/sdkhooks.py
bolt_api_sdk/_hooks/types.py
bolt_api_sdk/_version.py
bolt_api_sdk/account.py
bolt_api_sdk/basesdk.py
bolt_api_sdk/configuration.py
bolt_api_sdk/errors/__init__.py
bolt_api_sdk/errors/apierror.py
bolt_api_sdk/errors/bolterror.py
bolt_api_sdk/errors/capturetransactionop.py
bolt_api_sdk/errors/errors_bolt_api_response.py
bolt_api_sdk/errors/errors_oauth_server_response.py
bolt_api_sdk/errors/no_response_error.py
bolt_api_sdk/errors/responsevalidationerror.py
bolt_api_sdk/httpclient.py
bolt_api_sdk/models/__init__.py
bolt_api_sdk/models/account_details.py
bolt_api_sdk/models/account_details_address_view.py
bolt_api_sdk/models/account_identifier_status.py
bolt_api_sdk/models/addaddressop.py
bolt_api_sdk/models/addpaymentmethodop.py
bolt_api_sdk/models/address.py
bolt_api_sdk/models/address_account.py
bolt_api_sdk/models/address_change_request_metadata_view.py
bolt_api_sdk/models/address_change_view.py
bolt_api_sdk/models/address_view.py
bolt_api_sdk/models/amount_view.py
bolt_api_sdk/models/amounts.py
bolt_api_sdk/models/auth_rejection_details.py
bolt_api_sdk/models/auth_rejection_details_view.py
bolt_api_sdk/models/authorization_verification_status.py
bolt_api_sdk/models/authorizetransactionop.py
bolt_api_sdk/models/capture_status.py
bolt_api_sdk/models/capture_transaction_with_reference.py
bolt_api_sdk/models/capture_view.py
bolt_api_sdk/models/capturetransactionop.py
bolt_api_sdk/models/card_display_network.py
bolt_api_sdk/models/card_network.py
bolt_api_sdk/models/card_status.py
bolt_api_sdk/models/card_token_type.py
bolt_api_sdk/models/cart_add_on.py
bolt_api_sdk/models/cart_create.py
bolt_api_sdk/models/cart_discount.py
bolt_api_sdk/models/cart_fee.py
bolt_api_sdk/models/cart_item.py
bolt_api_sdk/models/cart_item_customization.py
bolt_api_sdk/models/cart_item_gift_option.py
bolt_api_sdk/models/cart_item_property.py
bolt_api_sdk/models/cart_item_property_view.py
bolt_api_sdk-0.5.6.dist-info/METADATA
bolt_api_sdk-0.5.6.dist-info/WHEEL
bolt_api_sdk-0.5.6.dist-info/licenses/LICENSE
bolt_api_sdk-0.5.6.dist-info/RECORD
